weibo_oauth/__init__.py
weibo_oauth/weibo.py
weibo_oauth-0.1.3.dist-info/LICENCE
weibo_oauth-0.1.3.dist-info/METADATA
weibo_oauth-0.1.3.dist-info/WHEEL
weibo_oauth-0.1.3.dist-info/top_level.txt
weibo_oauth-0.1.3.dist-info/RECORD
