Metadata-Version: 2.1
Name: weibo-oauth
Version: 0.1.3
Summary: 新浪微博API封装
Home-page: https://github.com/zcq100/weibo-oauth
Author: zcq100
Author-email: zcq100@gmail.com
License: UNKNOWN
Platform: UNKNOWN
Classifier: Programming Language :: Python :: 3
Classifier: License :: OSI Approved :: MIT License
Classifier: Topic :: Internet
Requires-Python: >=3.6
